wisest/__init__.py
wisest/cli.py
wisest/cost.py
wisest/currency.py
wisest/method.py
wisest/price.py
wisest/py.typed
wisest/rate.py
wisest-0.15.1.dist-info/METADATA
wisest-0.15.1.dist-info/WHEEL
wisest-0.15.1.dist-info/entry_points.txt
wisest-0.15.1.dist-info/licenses/LICENSE
wisest-0.15.1.dist-info/RECORD
