Metadata-Version: 2.4
Name: wisest
Version: 0.15.1
Author-email: narumi <toucans-cutouts0f@icloud.com>
License-File: LICENSE
Requires-Python: >=3.11
Requires-Dist: aiolimiter>=1.2.1
Requires-Dist: httpx>=0.27.2
Requires-Dist: pydantic>=2.9.2
Requires-Dist: rich>=13.9.4
Requires-Dist: tabulate>=0.9.0
Requires-Dist: typer>=0.15.2
